odoo/addons/multimedia_somconnexio/CHANGELOG.md
odoo/addons/multimedia_somconnexio/README.rst
odoo/addons/multimedia_somconnexio/__init__.py
odoo/addons/multimedia_somconnexio/__manifest__.py
odoo/addons/multimedia_somconnexio/data/product_attribute.xml
odoo/addons/multimedia_somconnexio/data/product_attribute_value.xml
odoo/addons/multimedia_somconnexio/data/product_category.xml
odoo/addons/multimedia_somconnexio/data/product_template.xml
odoo/addons/multimedia_somconnexio/data/product_template_attribute_line.xml
odoo/addons/multimedia_somconnexio/data/service_technology.xml
odoo/addons/multimedia_somconnexio/demo/service_supplier.xml
odoo/addons/multimedia_somconnexio/demo/service_technology_service_supplier.xml
odoo/addons/multimedia_somconnexio/listeners/__init__.py
odoo/addons/multimedia_somconnexio/listeners/crm_lead_listener.py
odoo/addons/multimedia_somconnexio/models/__init__.py
odoo/addons/multimedia_somconnexio/models/contract_contract.py
odoo/addons/multimedia_somconnexio/models/crm_lead.py
odoo/addons/multimedia_somconnexio/models/crm_lead_line.py
odoo/addons/multimedia_somconnexio/models/product_product.py
odoo/addons/multimedia_somconnexio/security/ir.model.access.csv
odoo/addons/multimedia_somconnexio/static/description/multimedia_contracts.png
odoo/addons/multimedia_somconnexio/tests/__init__.py
odoo/addons/multimedia_somconnexio/tests/helper_service.py
odoo/addons/multimedia_somconnexio/tests/utilities.py
odoo/addons/multimedia_somconnexio/tests/listeners/__init__.py
odoo/addons/multimedia_somconnexio/tests/listeners/test_crm_lead_listener.py
odoo/addons/multimedia_somconnexio/tests/models/__init__.py
odoo/addons/multimedia_somconnexio/tests/models/test_contract.py
odoo/addons/multimedia_somconnexio/tests/models/test_crm_lead.py
odoo/addons/multimedia_somconnexio/tests/models/test_crm_lead_line.py
odoo/addons/multimedia_somconnexio/tests/wizards/__init__.py
odoo/addons/multimedia_somconnexio/tests/wizards/test_crm_lead_add_multimedia_line.py
odoo_addon_multimedia_somconnexio-16.0.1.0.1.dist-info/METADATA
odoo_addon_multimedia_somconnexio-16.0.1.0.1.dist-info/WHEEL
odoo_addon_multimedia_somconnexio-16.0.1.0.1.dist-info/top_level.txt
odoo_addon_multimedia_somconnexio-16.0.1.0.1.dist-info/RECORD
